gptextual/__init__.py
gptextual/logging.py
gptextual/utils.py
gptextual/config/__init__.py
gptextual/config/app_config.py
gptextual/runtime/__init__.py
gptextual/runtime/conv_manager.py
gptextual/runtime/conversation.py
gptextual/runtime/models.py
gptextual/runtime/function_calling/__init__.py
gptextual/runtime/function_calling/function_call_support.py
gptextual/runtime/function_calling/functions.py
gptextual/runtime/langchain/__init__.py
gptextual/runtime/langchain/schema.py
gptextual/textual_ui/__init__.py
gptextual/textual_ui/app.py
gptextual/textual_ui/dark.tcss
gptextual/textual_ui/light.tcss
gptextual/textual_ui/screens/__init__.py
gptextual/textual_ui/screens/chat_screen.py
gptextual/textual_ui/screens/log_screen.py
gptextual/textual_ui/screens/message_info_modal.py
gptextual/textual_ui/screens/search_screen.py
gptextual/textual_ui/widgets/__init__.py
gptextual/textual_ui/widgets/chat.py
gptextual/textual_ui/widgets/chat_list.py
gptextual/textual_ui/widgets/chatbox.py
gptextual/textual_ui/widgets/footer.py
gptextual/textual_ui/widgets/header.py
gptextual/textual_ui/widgets/model_select.py
gptextual/textual_ui/widgets/search.py
gptextual/textual_ui/widgets/token_analysis.py
gptextual/textual_ui/widgets/typing_indicator.py
gptextual-0.0.9.dist-info/LICENSE
gptextual-0.0.9.dist-info/METADATA
gptextual-0.0.9.dist-info/WHEEL
gptextual-0.0.9.dist-info/entry_points.txt
gptextual-0.0.9.dist-info/top_level.txt
gptextual-0.0.9.dist-info/RECORD
