Metadata-Version: 2.1
Name: gptextual
Version: 0.0.9
Summary: A configurable, terminal based Chat client for LLMs built with Textual
Home-page: https://github.com/stefankirchfeld/gptextual
Author: Stefan Kirchfeld
Author-email: Stefan Kirchfeld <stefan.kirchfeld@gmail.com>
Maintainer-email: Stefan Kirchfeld <stefan.kirchfeld@gmail.com>
License: MIT License
Project-URL: Homepage, https://github.com/stefankirchfeld/gptextual
Project-URL: Repository, https://github.com/stefankirchfeld/gptextual
Keywords: gpt,chat,llm,chatgpt,langchain,openai,sap,textual,terminal
Classifier: Development Status :: 3 - Alpha
Classifier: Programming Language :: Python :: 3.10
Classifier: Programming Language :: Python :: 3.11
Classifier: Programming Language :: Python :: 3.12
Classifier: License :: OSI Approved :: MIT License
Classifier: Topic :: Scientific/Engineering :: Artificial Intelligence
Requires-Python: >=3.10
License-File: LICENSE
Requires-Dist: httpx ~=0.26.0
Requires-Dist: humanize ~=4.9.0
Requires-Dist: langchain ~=0.1.10
Requires-Dist: langchain-core ~=0.1.28
Requires-Dist: polars ~=0.20.7
Requires-Dist: pydantic ~=2.6.1
Requires-Dist: pyperclip ~=1.8.2
Requires-Dist: rich ~=13.7.0
Requires-Dist: shortuuid ~=1.0.11
Requires-Dist: textual ==0.50.1
Requires-Dist: tiktoken ~=0.5.2
Requires-Dist: toolong ==1.2.0
Requires-Dist: pyyaml ~=6.0.1
Requires-Dist: setuptools ~=69.1.0
Provides-Extra: all
Requires-Dist: langchain-openai ~=0.0.8 ; extra == 'all'
Requires-Dist: langchain-google-genai ~=0.0.9 ; extra == 'all'
Requires-Dist: generative-ai-hub-sdk ~=1.2.2 ; extra == 'all'
Requires-Dist: langchain-anthropic ~=0.1.1 ; extra == 'all'
Provides-Extra: anthropic
Requires-Dist: langchain-anthropic ~=0.1.1 ; extra == 'anthropic'
Provides-Extra: google
Requires-Dist: langchain-google-genai ~=0.0.9 ; extra == 'google'
Provides-Extra: openai
Requires-Dist: langchain-openai ~=0.0.8 ; extra == 'openai'
Provides-Extra: sap
Requires-Dist: generative-ai-hub-sdk ~=1.2.2 ; extra == 'sap'
